{
  "count": 4300,
  "uniques": 299,
  "clones": [
    {
      "timestamp": "2023-03-10T00:00:00Z",
      "count": 64,
      "uniques": 40
    },
    {
      "timestamp": "2023-03-11T00:00:00Z",
      "count": 311,
      "uniques": 123
    },
    {
      "timestamp": "2023-03-12T00:00:00Z",
      "count": 314,
      "uniques": 121
    },
    {
      "timestamp": "2023-03-13T00:00:00Z",
      "count": 309,
      "uniques": 126
    },
    {
      "timestamp": "2023-03-14T00:00:00Z",
      "count": 273,
      "uniques": 135
    },
    {
      "timestamp": "2023-03-15T00:00:00Z",
      "count": 283,
      "uniques": 135
    },
    {
      "timestamp": "2023-03-16T00:00:00Z",
      "count": 312,
      "uniques": 144
    },
    {
      "timestamp": "2023-03-17T00:00:00Z",
      "count": 305,
      "uniques": 117
    },
    {
      "timestamp": "2023-03-18T00:00:00Z",
      "count": 316,
      "uniques": 126
    },
    {
      "timestamp": "2023-03-19T00:00:00Z",
      "count": 319,
      "uniques": 131
    },
    {
      "timestamp": "2023-03-20T00:00:00Z",
      "count": 338,
      "uniques": 130
    },
    {
      "timestamp": "2023-03-21T00:00:00Z",
      "count": 332,
      "uniques": 135
    },
    {
      "timestamp": "2023-03-22T00:00:00Z",
      "count": 314,
      "uniques": 135
    },
    {
      "timestamp": "2023-03-23T00:00:00Z",
      "count": 286,
      "uniques": 133
    },
    {
      "timestamp": "2023-03-24T00:00:00Z",
      "count": 224,
      "uniques": 107
    }
  ]
}
